Metadata-Version: 2.4
Name: hypertools
Version: 0.8.1
Summary: A python package for visualizing and manipulating high-dimensional data
Home-page: https://github.com/ContextLab/hypertools
Download-URL: https://github.com/ContextLab/hypertools
Author: Contextual Dynamics Lab
Author-email: contextualdynamics@gmail.com
License: MIT
Classifier: Intended Audience :: Science/Research
Classifier: Programming Language :: Python :: 3.9
Classifier: Programming Language :: Python :: 3.10
Classifier: Programming Language :: Python :: 3.11
Classifier: Programming Language :: Python :: 3.12
Classifier: Topic :: Scientific/Engineering :: Visualization
Classifier: Topic :: Multimedia :: Graphics
Classifier: Operating System :: POSIX
Classifier: Operating System :: Unix
Classifier: Operating System :: MacOS
Requires-Python: >=3.9
License-File: LICENSE
Requires-Dist: PPCA>=0.0.2
Requires-Dist: scikit-learn>=1.4.0
Requires-Dist: pandas>=2.2.0
Requires-Dist: seaborn>=0.13.0
Requires-Dist: matplotlib>=3.8.0
Requires-Dist: scipy>=1.13.0
Requires-Dist: numpy>=2.0.0
Requires-Dist: umap-learn>=0.5.5
Requires-Dist: requests>=2.31.0
Requires-Dist: ipympl>=0.9.3
Requires-Dist: importlib_metadata>=1.0.0; python_version < "3.8"
Dynamic: author
Dynamic: author-email
Dynamic: classifier
Dynamic: description
Dynamic: download-url
Dynamic: home-page
Dynamic: license
Dynamic: license-file
Dynamic: requires-dist
Dynamic: requires-python
Dynamic: summary
